disco/__init__.py
disco/controllers/__init__.py
disco/controllers/amppi.py
disco/controllers/base.py
disco/models/__init__.py
disco/models/base.py
disco/models/cartpole.py
disco/models/pendulum.py
disco/utils/__init__.py
disco/utils/distributions.py
disco/utils/helper.py
disco/utils/spaces.py
disco/utils/utf.py
disco_rl-0.0.1.dist-info/LICENSE
disco_rl-0.0.1.dist-info/METADATA
disco_rl-0.0.1.dist-info/WHEEL
disco_rl-0.0.1.dist-info/top_level.txt
disco_rl-0.0.1.dist-info/RECORD
