Metadata-Version: 2.1
Name: disco-rl
Version: 0.0.1
Summary: This package provides a collection of modules and examples to quickly setup experiments using DISCO: Double Likelihood-free Inference Stochastic Control.
Home-page: https://github.com/lubaroli/disco
Author: Lucas Barcelos
Author-email: lucas.barcelos@sydney.edu.au
License: GPL
Platform: UNKNOWN
Classifier: Programming Language :: Python :: 3
Classifier: Operating System :: OS Independent
Requires-Dist: gym (>=0.12.4)
Requires-Dist: numpy (>=1.18.1)
Requires-Dist: matplotlib (>=3.1.2)
Requires-Dist: scipy (>=1.4.1)
Requires-Dist: torch (>=1.3)
